bomberman/__init__.py
bomberman/events.py
bomberman/game.py
bomberman/http_controller.py
bomberman/pygame_utils.py
bomberman/renderer.py
bomberman/stats.py
bomberman/objects/__init__.py
bomberman/objects/base.py
bomberman/objects/bomb.png
bomberman/objects/bomb.py
bomberman/objects/destructible.png
bomberman/objects/destructible.py
bomberman/objects/fire.png
bomberman/objects/fire.py
bomberman/objects/indestructible.png
bomberman/objects/indestructible.py
bomberman/objects/player.py
bomberman/objects/player_blue.png
bomberman/objects/player_blue_dead.png
bomberman/objects/player_default.png
bomberman/objects/player_default_dead.png
bomberman/objects/player_green.png
bomberman/objects/player_green_dead.png
bomberman/objects/player_red.png
bomberman/objects/player_red_dead.png
bomberman/objects/player_yellow.png
bomberman/objects/player_yellow_dead.png
bomberman/objects/powerup.py
bomberman/objects/powerup_bigger_explosion.png
bomberman/objects/powerup_more_bombs.png
bomberman/objects/powerup_speed.png
example_ai/__init__.py
example_ai/pure_randomness.py
tests/test_objects/__init__.py
tests/test_objects/test_player.py
bomberman_code_showdown-0.2.0.dist-info/METADATA
bomberman_code_showdown-0.2.0.dist-info/WHEEL
bomberman_code_showdown-0.2.0.dist-info/entry_points.txt
bomberman_code_showdown-0.2.0.dist-info/top_level.txt
bomberman_code_showdown-0.2.0.dist-info/RECORD
