Metadata-Version: 2.1
Name: bomberman-code-showdown
Version: 0.2.0
Summary: A bomberman game where you can control the characters through a HTTP API.
Home-page: https://gitlab.com/vladcalin/bomberman-code-showdown
Author: Vlad Calin
License: MIT
Platform: UNKNOWN
Requires-Dist: pygame
Requires-Dist: aiohttp
Provides-Extra: dev
Requires-Dist: pytest ; extra == 'dev'
Requires-Dist: pytest-mock ; extra == 'dev'
Requires-Dist: coverage ; extra == 'dev'
Requires-Dist: flake8 ; extra == 'dev'
Requires-Dist: twine ; extra == 'dev'
Requires-Dist: bump2version ; extra == 'dev'
Requires-Dist: pep8-naming ; extra == 'dev'
